odoo/addons/l10n_ec_ote/README.rst
odoo/addons/l10n_ec_ote/__init__.py
odoo/addons/l10n_ec_ote/__manifest__.py
odoo/addons/l10n_ec_ote/data/l10n.ec.parish.csv
odoo/addons/l10n_ec_ote/data/res.city.csv
odoo/addons/l10n_ec_ote/data/res.country.state.csv
odoo/addons/l10n_ec_ote/i18n/es_EC.po
odoo/addons/l10n_ec_ote/i18n/l10n_ec_ote.pot
odoo/addons/l10n_ec_ote/models/__init__.py
odoo/addons/l10n_ec_ote/models/l10n_ec_parish.py
odoo/addons/l10n_ec_ote/models/res_company.py
odoo/addons/l10n_ec_ote/models/res_partner.py
odoo/addons/l10n_ec_ote/readme/CONTRIBUTORS.rst
odoo/addons/l10n_ec_ote/readme/DESCRIPTION.rst
odoo/addons/l10n_ec_ote/security/ir.model.access.csv
odoo/addons/l10n_ec_ote/static/description/icon.png
odoo/addons/l10n_ec_ote/static/description/index.html
odoo/addons/l10n_ec_ote/views/l10n_ec_parish_view.xml
odoo/addons/l10n_ec_ote/views/res_city_view.xml
odoo/addons/l10n_ec_ote/views/res_company.xml
odoo/addons/l10n_ec_ote/views/res_partner.xml
odoo_addon_l10n_ec_ote-15.0.1.0.0.6.dist-info/METADATA
odoo_addon_l10n_ec_ote-15.0.1.0.0.6.dist-info/WHEEL
odoo_addon_l10n_ec_ote-15.0.1.0.0.6.dist-info/top_level.txt
odoo_addon_l10n_ec_ote-15.0.1.0.0.6.dist-info/RECORD
