Metadata-Version: 2.1
Name: odoo-addon-l10n-ec-ote
Version: 15.0.1.0.0.6
Summary: OTE for Ecuador
Home-page: https://github.com/OCA/l10n-ecuador
Author: Odoo Community Association (OCA), Odoo-EC
Author-email: support@odoo-community.org
License: LGPL-3
Platform: UNKNOWN
Classifier: Programming Language :: Python
Classifier: Framework :: Odoo
Classifier: Framework :: Odoo :: 15.0
Classifier: License :: OSI Approved :: GNU Lesser General Public License v3 (LGPLv3)
Requires-Python: >=3.8
Requires-Dist: odoo <15.1dev,>=15.0a
